[
  {
    "id": 1,
    "name": "Batata Asterix",
    "desc": "A batata-asterix.",
    "state": false,
    "categoria": "Batata",
    "value": "14.90",
    "image": "../../src/assets/BatataAsterix.jpg"
  },
  {
    "id": 2,
    "name": "Batata Doce",
    "state": true,
    "categoria": "Batata",
    "desc": "A batata-doce.",
    "value": "9.90",
    "image": "../../src/assets/BatataDoce.webp"
  },
  {
    "id": 3,
    "name": "Batata Salsa",
    "state": false,
    "categoria": "Batata",
    "desc": "A Batata Salsa.",
    "value": "12.99",
    "image": "../../src/assets/BatataSalsa.webp"
  },
  {
    "id": 4,
    "name": "Batata Yukon Gold",
    "state": true,
    "categoria": "Batata",
    "desc": "A batata Yukon Gold.",
    "value": "15.00",
    "image": "../../src/assets/BatataYukonGold.jpg"
  },
  {
    "id": 5,
    "name": "Batata Inglesa",
    "state": false,
    "categoria": "Batata",
    "desc": "A Batata Inglesa.",
    "value": "15.00",
    "image": "../../src/assets/BatataInglesa.png"
  },
  {
    "id": 6,
    "name": "Batata Inglesa",
    "state": false,
    "categoria": "Batata",
    "desc": "A Batata Inglesa.",
    "value": "15.00",
    "image": "../../src/assets/BatataInglesa.png"
  }
]
